{"cameraMode":{"drawMode":0,"name":"Shaded","section":"Shading Mode"},"sceneLighting":false,"audioPlay":false,"sceneViewState":{"showFog":true,"showMaterialUpdate":false,"showSkybox":false,"showFlares":true,"showImageEffects":true,"showParticleSystems":true},"in2DMode":false,"pivot":{"x":0.7955681085586548,"y":-7.766912937164307,"z":7.087568283081055},"rotation":{"x":-0.38098952174186709,"y":-0.06319431960582733,"z":0.026052281260490419,"w":-0.922101616859436},"size":11.026543617248536,"orthographic":false}